videotrim/__init__.py
videotrim/cli.py
videotrim/detection.py
videotrim/io.py
videotrim/trim.py
videotrim/utils.py
videotrim-0.2.0.dist-info/WHEEL
videotrim-0.2.0.dist-info/entry_points.txt
videotrim-0.2.0.dist-info/METADATA
videotrim-0.2.0.dist-info/RECORD
