Metadata-Version: 2.3
Name: videotrim
Version: 0.2.0
Summary: A fast, efficient video trimming and manipulation toolkit
Author: Talmo Pereira
Author-email: Talmo Pereira <talmo@talmolab.org>
Requires-Dist: click>=8.3.0
Requires-Dist: numpy>=1.24.0
Requires-Dist: imageio>=2.34.0
Requires-Dist: imageio-ffmpeg>=0.4.9
Requires-Dist: av>=12.0.0
Requires-Dist: opencv-python>=4.11.0.86
Requires-Dist: matplotlib>=3.10.7
Requires-Dist: scikit-image>=0.25.2
Requires-Dist: scipy>=1.16.2
Requires-Dist: tqdm>=4.67.1
Requires-Dist: pytest>=8.0.0 ; extra == 'dev'
Requires-Dist: pytest-cov>=4.1.0 ; extra == 'dev'
Requires-Dist: ruff>=0.3.0 ; extra == 'dev'
Requires-Python: >=3.12
Provides-Extra: dev
